Metadata-Version: 1.0
Name: randomtable1
Version: 0.1.0
Summary: Super useful library
Home-page: UNKNOWN
Author: Tm
Author-email: tomasz_matuszewski@o2.pl
License: UNKNOWN
Platform: UNKNOWN
